loeg/__init__.py
loeg/__main__.py
loeg/py.typed
loeg-0.2.0.dist-info/WHEEL
loeg-0.2.0.dist-info/entry_points.txt
loeg-0.2.0.dist-info/METADATA
loeg-0.2.0.dist-info/RECORD
