Metadata-Version: 2.3
Name: loeg
Version: 0.2.0
Summary: Løg: Quick log prettifier
Author: sorenmulli
Author-email: sorenmulli <soren@vholm.dk>
Requires-Dist: colorama>=0.4.6
Requires-Python: >=3.12
